fastapi_plugins_pika/__init__.py
fastapi_plugins_pika/schema/__init__.py
fastapi_plugins_pika/schema/rtcSchema.py
fastapi_plugins_pika/service/__init__.py
fastapi_plugins_pika/service/rtcService.py
fastapi_plugins_pika/service/rtcServiceImpl/__init__.py
fastapi_plugins_pika/service/rtcServiceImpl/AccessToken.py
fastapi_plugins_pika/service/rtcServiceImpl/RtcTokenBuilder.py
fastapi_plugins_pika-0.1.1.dist-info/WHEEL
fastapi_plugins_pika-0.1.1.dist-info/METADATA
fastapi_plugins_pika-0.1.1.dist-info/RECORD
